logtube/__init__.py
logtube/core.py
logtube/event.py
logtube/job_commiter.py
logtube/logger.py
logtube/output.py
logtube/output_test.py
logtube/utils.py
logtube/utils_test.py
logtube-1.0.1.dist-info/LICENSE
logtube-1.0.1.dist-info/METADATA
logtube-1.0.1.dist-info/WHEEL
logtube-1.0.1.dist-info/top_level.txt
logtube-1.0.1.dist-info/RECORD
