Metadata-Version: 2.1
Name: logtube
Version: 1.0.1
Summary: Logtube Python SDK
Home-page: https://github.com/logtube/logtube-py
Author: Guo Y.K.
Author-email: hi@guoyk.net
License: UNKNOWN
Project-URL: Bug Tracker, https://github.com/logtube/logtube-py/issues
Platform: UNKNOWN
Classifier: Programming Language :: Python :: 3
Classifier: License :: OSI Approved :: MIT License
Classifier: Operating System :: OS Independent
Requires-Python: >=3.6
License-File: LICENSE
